logicalbin/BinSum.py
logicalbin/LGates.py
logicalbin/__init__.py
logicalbin-1.0.dist-info/LICENSE.txt
logicalbin-1.0.dist-info/METADATA
logicalbin-1.0.dist-info/WHEEL
logicalbin-1.0.dist-info/top_level.txt
logicalbin-1.0.dist-info/RECORD
