Metadata-Version: 2.1
Name: logicalbin
Version: 1.0
Author: BlueJFlamesLab
License: MIT
Requires-Python: >=3.0
License-File: LICENSE.txt
